ddmin/__init__.py
ddmin/ddmin.py
ddmin-0.0.1.dist-info/DESCRIPTION.rst
ddmin-0.0.1.dist-info/METADATA
ddmin-0.0.1.dist-info/RECORD
ddmin-0.0.1.dist-info/WHEEL
ddmin-0.0.1.dist-info/metadata.json
ddmin-0.0.1.dist-info/top_level.txt
