Metadata-Version: 2.0
Name: ddmin
Version: 0.0.1
Summary: Elementary implementation of delta debugging algorithm
Home-page: https://github.com/hydraseq/ddmin
Author: Efrain Olivares
Author-email: efrain.olivares@gmail.com
License: UNKNOWN
Platform: UNKNOWN
Classifier: Programming Language :: Python :: 3
Classifier: License :: OSI Approved :: MIT License
Classifier: Operating System :: OS Independent
